ftrack_api/__init__.py
ftrack_api/_centralized_storage_scenario.py
ftrack_api/_python_ntpath.py
ftrack_api/_version.py
ftrack_api/accessor/__init__.py
ftrack_api/accessor/base.py
ftrack_api/accessor/disk.py
ftrack_api/accessor/server.py
ftrack_api/attribute.py
ftrack_api/cache.py
ftrack_api/collection.py
ftrack_api/data.py
ftrack_api/entity/__init__.py
ftrack_api/entity/asset_version.py
ftrack_api/entity/base.py
ftrack_api/entity/component.py
ftrack_api/entity/factory.py
ftrack_api/entity/job.py
ftrack_api/entity/location.py
ftrack_api/entity/note.py
ftrack_api/entity/project_schema.py
ftrack_api/entity/user.py
ftrack_api/event/__init__.py
ftrack_api/event/base.py
ftrack_api/event/expression.py
ftrack_api/event/hub.py
ftrack_api/event/subscriber.py
ftrack_api/event/subscription.py
ftrack_api/exception.py
ftrack_api/formatter.py
ftrack_api/inspection.py
ftrack_api/logging.py
ftrack_api/operation.py
ftrack_api/plugin.py
ftrack_api/query.py
ftrack_api/resource_identifier_transformer/__init__.py
ftrack_api/resource_identifier_transformer/base.py
ftrack_api/session.py
ftrack_api/structure/__init__.py
ftrack_api/structure/base.py
ftrack_api/structure/entity_id.py
ftrack_api/structure/id.py
ftrack_api/structure/origin.py
ftrack_api/structure/standard.py
ftrack_api/symbol.py
ftrack_python_api-3.0.6.dist-info/LICENSE.python
ftrack_python_api-3.0.6.dist-info/LICENSE.txt
ftrack_python_api-3.0.6.dist-info/METADATA
ftrack_python_api-3.0.6.dist-info/WHEEL
ftrack_python_api-3.0.6.dist-info/RECORD
