Metadata-Version: 2.1
Name: ftrack-python-api
Version: 3.0.6
Summary: Python API for ftrack.
Home-page: https://github.com/ftrackhq/ftrack-python
License: Apache-2.0
Author: ftrack
Author-email: support@ftrack.com
Requires-Python: >=3.8,<4.0
Classifier: License :: OSI Approved :: Apache Software License
Classifier: Programming Language :: Python :: 3
Classifier: Programming Language :: Python :: 3.8
Classifier: Programming Language :: Python :: 3.9
Classifier: Programming Language :: Python :: 3.10
Classifier: Programming Language :: Python :: 3.11
Classifier: Programming Language :: Python :: 3.12
Classifier: Programming Language :: Python :: 3.13
Requires-Dist: arrow (>=0.4.4,<1)
Requires-Dist: clique (==1.6.1)
Requires-Dist: platformdirs (>=4.0.0,<5)
Requires-Dist: pyparsing (>=2.0,<3)
Requires-Dist: requests (>=2,<3)
Requires-Dist: sphinx-notfound-page (>=1.0.4,<2.0.0)
Requires-Dist: websocket-client (>=0.40.0,<1)
Project-URL: Documentation, https://developer.ftrack.com/api-clients/python/
Project-URL: Repository, https://github.com/ftrackhq/ftrack-python
